nosql/__init__.py
nosql/base.py
nosql/mongo.py
nosql/redis.py
taskqueue/__init__.py
taskqueue/base.py
taskqueue/rabbitmq.py
taskqueue/redis_config.py
taskqueue/redque.py
zync/__init__.py
zync/config.py
zync/data_store.py
zync/item.py
zync/normalizer.py
zync/normalmodel.py
zync/registry.py
zync/sync.py
zync/zync.py
pyzync-0.1.0.dist-info/WHEEL
pyzync-0.1.0.dist-info/METADATA
pyzync-0.1.0.dist-info/RECORD
