Metadata-Version: 2.1
Name: pyzync
Version: 0.1.0
Summary: An integration framework for continuously syncing data
License: Proprietary
Author: Joseph DeWitt
Author-email: joseph@zync.me
Requires-Python: >=3.8,<4.0
Classifier: License :: Other/Proprietary License
Classifier: Programming Language :: Python :: 3
Classifier: Programming Language :: Python :: 3.8
Classifier: Programming Language :: Python :: 3.9
Classifier: Programming Language :: Python :: 3.10
Requires-Dist: pydantic (>=1.9.1,<2.0.0)
Requires-Dist: pymongo (>=4.3.2,<5.0.0)
Requires-Dist: redis (>=4.3.4,<5.0.0)
Requires-Dist: rq (>=1.11.1,<2.0.0)
